alembic_autoscan/__init__.py
alembic_autoscan/__main__.py
alembic_autoscan/cli.py
alembic_autoscan/integration.py
alembic_autoscan/scanner.py
alembic_autoscan-1.0.0.dist-info/METADATA
alembic_autoscan-1.0.0.dist-info/WHEEL
alembic_autoscan-1.0.0.dist-info/entry_points.txt
alembic_autoscan-1.0.0.dist-info/licenses/LICENSE
alembic_autoscan-1.0.0.dist-info/RECORD
