Metadata-Version: 2.4
Name: alembic-autoscan
Version: 1.0.0
Summary: Automatically discover and import SQLAlchemy models for Alembic migrations
Project-URL: Homepage, https://github.com/tonlls/alembic-autoscan
Project-URL: Repository, https://github.com/tonlls/alembic-autoscan
Project-URL: Issues, https://github.com/tonlls/alembic-autoscan/issues
Project-URL: Documentation, https://github.com/tonlls/alembic-autoscan#readme
Author-email: tonlls <tonlls@users.noreply.github.com>
License: MIT
License-File: LICENSE
Keywords: alembic,automation,migrations,sqlalchemy
Classifier: Development Status :: 4 - Beta
Classifier: Intended Audience :: Developers
Classifier: License :: OSI Approved :: MIT License
Classifier: Programming Language :: Python :: 3
Classifier: Programming Language :: Python :: 3.8
Classifier: Programming Language :: Python :: 3.9
Classifier: Programming Language :: Python :: 3.10
Classifier: Programming Language :: Python :: 3.11
Classifier: Programming Language :: Python :: 3.12
Classifier: Topic :: Database
Classifier: Topic :: Software Development :: Libraries :: Python Modules
Requires-Python: >=3.8
Requires-Dist: alembic>=1.7.0
Requires-Dist: sqlalchemy>=1.4.0
Provides-Extra: dev
Requires-Dist: mypy>=1.0.0; extra == 'dev'
Requires-Dist: pre-commit>=3.5.0; extra == 'dev'
Requires-Dist: pytest-cov>=4.0.0; extra == 'dev'
Requires-Dist: pytest>=7.0.0; extra == 'dev'
Requires-Dist: ruff>=0.1.0; extra == 'dev'
